{
    "title": "Armenien",
    "slug": "armenia",
    "baseInfo": {
        "name": {
            "common": "Armenien",
            "official": "Republik Armenien",
            "native": [
                {
                    "languageCode": "hy",
                    "official": "Հայաստանի Հանրապետություն",
                    "common": "Հայաստան"
                }
            ]
        },
        "capital": "Jerewan",
        "region": "Asien",
        "subregion": "Vorderasien",
        "languages": [{ "languageCode": "hy", "name": "Armenisch" }],
        "currencies": [
            { "currencyCode": "AMD", "name": "Armenischer Dram", "symbol": "֏" }
        ],
        "flag": "🇦🇲",
        "codes": { "cca2": "AM", "cca3": "ARM", "ccn3": "051" },
        "coordinates": { "latitude": 40, "longitude": 45 }
    }
}
