{
    "title": "Polen",
    "slug": "poland",
    "baseInfo": {
        "name": {
            "common": "Polen",
            "official": "Republik Polen",
            "native": [
                {
                    "languageCode": "pl",
                    "official": "Rzeczpospolita Polska",
                    "common": "Polska"
                }
            ]
        },
        "capital": "Warsaw",
        "region": "Europe",
        "subregion": "Eastern Europe",
        "languages": [{ "languageCode": "pl", "name": "Polnisch" }],
        "currencies": [
            { "currencyCode": "PLN", "name": "Polnischer Złoty", "symbol": "zł" }
        ],
        "flag": "🇵🇱",
        "codes": { "cca2": "PL", "cca3": "POL", "ccn3": "616" },
        "coordinates": { "latitude": 52, "longitude": 20 }
    }
}
